neuralforge/__init__.py
neuralforge/tensor_operations.py
neuralforge/utils.py
neuralforge/nn/__init__.py
neuralforge/nn/layers.py
neuralforge/nn/optim.py
neuralforge-0.0.15.dist-info/LICENSE
neuralforge-0.0.15.dist-info/METADATA
neuralforge-0.0.15.dist-info/WHEEL
neuralforge-0.0.15.dist-info/top_level.txt
neuralforge-0.0.15.dist-info/RECORD
