Metadata-Version: 2.1
Name: neuralforge
Version: 0.0.15
Summary: An educational framework similar to PyTorch, built to be interpretable and easy to implement.
Home-page: https://github.com/eduardoleao052/Autograd-from-scratch
Author: Eduardo Leitao da Cunha Opice Leao
Author-email: eduardoleao052@gmail.com
Maintainer: Eduardo Leitao da Cunha Opice Leao
License: MIT
Keywords: autograd deep-learning machine-learning ai numpy python
Requires-Python: >=3.0
License-File: LICENSE
Requires-Dist: numpy
Requires-Dist: neuralforge
